{
  "accentColor": "{{appsmith.theme.colors.primaryColor}}",
  "allowCurrencyChange": false,
  "animateLoading": true,
  "autoFocus": false,
  "borderRadius": "{{appsmith.theme.borderRadius.appBorderRadius}}",
  "bottomRow": 7,
  "boxShadow": "none",
  "decimals": 0,
  "defaultCurrencyCode": "INR",
  "defaultText": "",
  "dynamicBindingPathList": [
    {
      "key": "accentColor"
    },
    {
      "key": "borderRadius"
    }
  ],
  "dynamicHeight": "FIXED",
  "iconAlign": "left",
  "isDisabled": false,
  "isLoading": false,
  "isRequired": false,
  "isVisible": true,
  "key": "rk561cqek5",
  "label": "Label",
  "labelAlignment": "left",
  "labelPosition": "Top",
  "labelStyle": "",
  "labelTextSize": "0.875rem",
  "labelWidth": 5,
  "leftColumn": 0,
  "maxDynamicHeight": 9000,
  "minDynamicHeight": 4,
  "minWidth": 450,
  "mobileBottomRow": 7,
  "mobileLeftColumn": 0,
  "mobileRightColumn": 20,
  "mobileTopRow": 0,
  "needsErrorInfo": false,
  "parentColumnSpace": 13.03125,
  "parentId": "0",
  "parentRowSpace": 10,
  "renderMode": "CANVAS",
  "resetOnSubmit": true,
  "responsiveBehavior": "fill",
  "rightColumn": 20,
  "showStepArrows": false,
  "topRow": 0,
  "type": "CURRENCY_INPUT_WIDGET",
  "version": 1,
  "widgetId": "lbe33ol8j0",
  "widgetName": "CurrencyInput1"
}